{"implements":["ghidra.app.util.bin.StructConverter"],"javadoc":"","static":false,"extends":"java.lang.Object","methods":[{"javadoc":"","static":false,"name":"getResourceObject","comment":"","params":[],"throws":[],"return":{"type_long":"java.lang.Object","comment":"","type_short":"Object"}},{"javadoc":"Returns the resource type.\n@return the resource type","static":false,"name":"getType","comment":"Returns the resource type.","params":[],"throws":[],"return":{"type_long":"int","comment":"the resource type","type_short":"int"}},{"javadoc":"","static":false,"name":"getTypeAsString","comment":"","params":[],"throws":[],"return":{"type_long":"java.lang.String","comment":"","type_short":"String"}},{"javadoc":"Returns the number of resources of this type\n in map minus 1.\n@return the number of resources","static":false,"name":"getNumberOfResources","comment":"Returns the number of resources of this type\n in map minus 1.","params":[],"throws":[],"return":{"type_long":"short","comment":"the number of resources","type_short":"short"}},{"javadoc":"Returns the offset from the beginning of the \n resource type list to reference list for this type.\n@return the offset to reference list","static":false,"name":"getOffsetToReferenceList","comment":"Returns the offset from the beginning of the \n resource type list to reference list for this type.","params":[],"throws":[],"return":{"type_long":"short","comment":"the offset to reference list","type_short":"short"}},{"javadoc":"","static":false,"name":"getReferenceList","comment":"","params":[],"throws":[],"return":{"type_long":"java.util.List<ghidra.app.util.bin.format.macos.rm.ReferenceListEntry>","comment":"","type_short":"List"}},{"javadoc":"","static":false,"name":"toDataType","comment":"","params":[],"throws":[{"type_long":"ghidra.util.exception.DuplicateNameException","comment":"","type_short":"DuplicateNameException"},{"type_long":"java.io.IOException","comment":"","type_short":"IOException"}],"return":{"type_long":"ghidra.program.model.data.DataType","comment":"","type_short":"DataType"}}],"name":"ResourceType","comment":"","fields":[]}
