{"implements":[],"javadoc":"VersionControlAction is an abstract class that can be extended by each specific version\n control action to be taken on a domain file.","static":false,"extends":"ghidra.framework.main.datatable.DomainFileProviderContextAction","methods":[{"javadoc":"","static":false,"name":"<init>","comment":"","params":[{"type_long":"java.lang.String","name":"name","comment":"","type_short":"String"},{"type_long":"java.lang.String","name":"owner","comment":"","type_short":"String"},{"type_long":"ghidra.framework.plugintool.PluginTool","name":"tool","comment":"","type_short":"PluginTool"}],"throws":[],"return":{"type_long":"void","comment":"","type_short":"void"}},{"javadoc":"Returns true if there is at least one of the provided domain files can be \n or is version controlled.","static":false,"name":"isAddToPopup","comment":"Returns true if there is at least one of the provided domain files can be \n or is version controlled.","params":[{"type_long":"ghidra.framework.main.datatable.DomainFileProvider","name":"context","comment":"","type_short":"DomainFileProvider"}],"throws":[],"return":{"type_long":"boolean","comment":"","type_short":"boolean"}}],"name":"VersionControlAction","comment":"VersionControlAction is an abstract class that can be extended by each specific version\n control action to be taken on a domain file.","fields":[]}
