{"implements":[],"javadoc":"","static":false,"extends":"generic.test.AbstractGenericTest","methods":[{"javadoc":"","static":false,"name":"<init>","comment":"","params":[],"throws":[],"return":{"type_long":"void","comment":"","type_short":"void"}},{"javadoc":"","static":false,"name":"setUp","comment":"","params":[],"throws":[{"type_long":"java.lang.Exception","comment":"","type_short":"Exception"}],"return":{"type_long":"void","comment":"","type_short":"void"}},{"javadoc":"","static":false,"name":"testTwoSpacesWithSecondRangeAt0","comment":"","params":[],"throws":[{"type_long":"java.lang.Exception","comment":"","type_short":"Exception"}],"return":{"type_long":"void","comment":"","type_short":"void"}},{"javadoc":"","static":false,"name":"testAddOverlappingRangeWithSameObject","comment":"","params":[],"throws":[],"return":{"type_long":"void","comment":"","type_short":"void"}},{"javadoc":"","static":false,"name":"testAddAdjoiningRangesWithSameObject","comment":"","params":[],"throws":[],"return":{"type_long":"void","comment":"","type_short":"void"}},{"javadoc":"","static":false,"name":"testAddAdjoiningRangesWithDifferentObject","comment":"","params":[],"throws":[],"return":{"type_long":"void","comment":"","type_short":"void"}},{"javadoc":"","static":false,"name":"testAddCompletelyCoveredRangeWithDifferentObject","comment":"","params":[],"throws":[],"return":{"type_long":"void","comment":"","type_short":"void"}},{"javadoc":"","static":false,"name":"testAddSingleAddressRangeInMiddleOfExistingRangeWithDifferentObject","comment":"","params":[],"throws":[],"return":{"type_long":"void","comment":"","type_short":"void"}}],"name":"AddressRangeObjectMapTest","comment":"","fields":[]}
