{"implements":[],"javadoc":"","static":false,"extends":"generic.test.AbstractGenericTest","methods":[{"javadoc":"","static":false,"name":"<init>","comment":"","params":[],"throws":[],"return":{"type_long":"void","comment":"","type_short":"void"}},{"javadoc":"","static":false,"name":"testTimeout","comment":"","params":[],"throws":[],"return":{"type_long":"void","comment":"","type_short":"void"}},{"javadoc":"","static":false,"name":"testTimeout_Callback","comment":"","params":[],"throws":[],"return":{"type_long":"void","comment":"","type_short":"void"}}],"name":"TimeoutTaskMonitorTest","comment":"","fields":[]}
