{"implements":[],"javadoc":"File Searcher Exception Handler...","static":true,"extends":"java.lang.Exception","methods":[{"javadoc":"","static":false,"name":"<init>","comment":"","params":[{"type_long":"java.lang.String","name":"ExceptionString","comment":"","type_short":"String"}],"throws":[],"return":{"type_long":"void","comment":"","type_short":"void"}}],"name":"FileSearcherException","comment":"File Searcher Exception Handler...","fields":[{"type_long":"long","javadoc":"","static":true,"name":"serialVersionUID","comment":"","type_short":"long","constant_value":"0"}]}
