{"implements":["ghidra.framework.cmd.Command"],"javadoc":"Command to add a memory block.","static":false,"extends":"java.lang.Object","methods":[{"javadoc":"Construct a new AddMemoryBlockCmd\n@param name block name\n@param comment block comments\n@param source block source\n@param start starting address of the block\n@param length block length\n@param read read permissions\n@param write write permissions\n@param execute execute permissions\n@param isVolatile volatile setting\n@param initialValue initial byte value\n@param blockType type of block to add: MemoryBlockType.DEFAULT, \n MemoryBlockType.OVERLAY, or MemoryBlockType.BIT_MAPPED or MemoryBlockType.BYTE_MAPPED\n@param baseAddr base address for the source address if the block type\n is TYPE_BIT_MAPPED or TYPE_BYTE_MAPPED; otherwise, null","static":false,"name":"<init>","comment":"Construct a new AddMemoryBlockCmd","params":[{"type_long":"java.lang.String","name":"name","comment":"block name","type_short":"String"},{"type_long":"java.lang.String","name":"comment","comment":"block comments","type_short":"String"},{"type_long":"java.lang.String","name":"source","comment":"block source","type_short":"String"},{"type_long":"ghidra.program.model.address.Address","name":"start","comment":"starting address of the block","type_short":"Address"},{"type_long":"int","name":"length","comment":"block length","type_short":"int"},{"type_long":"boolean","name":"read","comment":"read permissions","type_short":"boolean"},{"type_long":"boolean","name":"write","comment":"write permissions","type_short":"boolean"},{"type_long":"boolean","name":"execute","comment":"execute permissions","type_short":"boolean"},{"type_long":"boolean","name":"isVolatile","comment":"volatile setting","type_short":"boolean"},{"type_long":"byte","name":"initialValue","comment":"initial byte value","type_short":"byte"},{"type_long":"ghidra.program.model.mem.MemoryBlockType","name":"blockType","comment":"type of block to add: MemoryBlockType.DEFAULT, \n MemoryBlockType.OVERLAY, or MemoryBlockType.BIT_MAPPED or MemoryBlockType.BYTE_MAPPED","type_short":"MemoryBlockType"},{"type_long":"ghidra.program.model.address.Address","name":"baseAddr","comment":"base address for the source address if the block type\n is TYPE_BIT_MAPPED or TYPE_BYTE_MAPPED; otherwise, null","type_short":"Address"},{"type_long":"boolean","name":"isInitialized","comment":"","type_short":"boolean"}],"throws":[],"return":{"type_long":"void","comment":"","type_short":"void"}},{"javadoc":"@see ghidra.framework.cmd.Command#applyTo(ghidra.framework.model.DomainObject)","static":false,"name":"applyTo","comment":"","params":[{"type_long":"ghidra.framework.model.DomainObject","name":"obj","comment":"","type_short":"DomainObject"}],"throws":[],"return":{"type_long":"boolean","comment":"","type_short":"boolean"}},{"javadoc":"@see ghidra.framework.cmd.Command#getName()","static":false,"name":"getName","comment":"","params":[],"throws":[],"return":{"type_long":"java.lang.String","comment":"","type_short":"String"}},{"javadoc":"@see ghidra.framework.cmd.Command#getStatusMsg()","static":false,"name":"getStatusMsg","comment":"","params":[],"throws":[],"return":{"type_long":"java.lang.String","comment":"","type_short":"String"}}],"name":"AddMemoryBlockCmd","comment":"Command to add a memory block.","fields":[]}
