{"implements":[],"javadoc":"","static":false,"extends":"java.lang.Object","methods":[{"javadoc":"","static":false,"name":"getEquate","comment":"","params":[],"throws":[],"return":{"type_long":"ghidra.program.model.symbol.Equate","comment":"","type_short":"Equate"}},{"javadoc":"","static":false,"name":"getEntryName","comment":"","params":[],"throws":[],"return":{"type_long":"java.lang.String","comment":"","type_short":"String"}},{"javadoc":"","static":false,"name":"getPath","comment":"","params":[],"throws":[],"return":{"type_long":"java.lang.String","comment":"","type_short":"String"}},{"javadoc":"","static":false,"name":"getRefCount","comment":"","params":[],"throws":[],"return":{"type_long":"int","comment":"","type_short":"int"}},{"javadoc":"","static":false,"name":"getEnumDataType","comment":"","params":[],"throws":[],"return":{"type_long":"ghidra.program.model.data.Enum","comment":"","type_short":"Enum"}},{"javadoc":"","static":false,"name":"toString","comment":"","params":[],"throws":[],"return":{"type_long":"java.lang.String","comment":"","type_short":"String"}},{"javadoc":"","static":false,"name":"hashCode","comment":"","params":[],"throws":[],"return":{"type_long":"int","comment":"","type_short":"int"}},{"javadoc":"","static":false,"name":"equals","comment":"","params":[{"type_long":"java.lang.Object","name":"obj","comment":"","type_short":"Object"}],"throws":[],"return":{"type_long":"boolean","comment":"","type_short":"boolean"}}],"name":"EquateRowObject","comment":"","fields":[]}
