{"implements":[],"javadoc":"A base renderer class to define shared logic needed to render a vertex\n@param <V> the vertex type\n@param <E> the edge type","static":false,"extends":"edu.uci.ics.jung.visualization.renderers.BasicVertexRenderer","methods":[{"javadoc":"","static":false,"name":"<init>","comment":"","params":[],"throws":[],"return":{"type_long":"void","comment":"","type_short":"void"}},{"javadoc":"Uses the render context to create a compact shape for the given vertex\n@param rc the render context\n@param layout the layout\n@param vertex the vertex\n@return the vertex shape\n@see VertexShapeProvider#getFullShape()","static":false,"name":"getFullShape","comment":"Uses the render context to create a compact shape for the given vertex","params":[{"type_long":"edu.uci.ics.jung.visualization.RenderContext<V,E>","name":"rc","comment":"the render context","type_short":"RenderContext"},{"type_long":"edu.uci.ics.jung.algorithms.layout.Layout<V,E>","name":"layout","comment":"the layout","type_short":"Layout"},{"type_long":"V","name":"vertex","comment":"the vertex","type_short":"V"}],"throws":[],"return":{"type_long":"java.awt.Shape","comment":"the vertex shape","type_short":"Shape"}}],"name":"AbstractVisualVertexRenderer","comment":"A base renderer class to define shared logic needed to render a vertex","fields":[]}
